bounce_mail_identifier/__init__.py
bounce_mail_identifier/bounce_mail_handler.py
bounce_mail_identifier/email_extractor.py
bounce_mail_identifier-1.0.2.dist-info/METADATA
bounce_mail_identifier-1.0.2.dist-info/WHEEL
bounce_mail_identifier-1.0.2.dist-info/entry_points.txt
bounce_mail_identifier-1.0.2.dist-info/top_level.txt
bounce_mail_identifier-1.0.2.dist-info/RECORD
