Metadata-Version: 2.1
Name: bounce-mail-identifier
Version: 1.0.2
Summary: A package to fetch bounce emails and save them to an Excel file
Author: Around With Us
Author-email: mscrabe@gmail.com
Keywords: Bounce Emails,Email Handling,Python package,Email Processing,Email Automation
Classifier: Development Status :: 5 - Production/Stable
Classifier: Topic :: Software Development :: Libraries :: Python Modules
Classifier: Programming Language :: Python :: 3
Classifier: License :: OSI Approved :: MIT License
Classifier: Operating System :: OS Independent
Requires-Python: >=3.6
Requires-Dist: pandas
Requires-Dist: openpyxl
